nastranpy/__init__.py
nastranpy/setup_logging.py
nastranpy/bdf/__init__.py
nastranpy/bdf/case_set.py
nastranpy/bdf/id_pattern.py
nastranpy/bdf/misc.py
nastranpy/bdf/model.py
nastranpy/bdf/observable.py
nastranpy/bdf/read_bdf.py
nastranpy/bdf/write_bdf.py
nastranpy/bdf/cards/__init__.py
nastranpy/bdf/cards/card.py
nastranpy/bdf/cards/card_factory.py
nastranpy/bdf/cards/card_interfaces.py
nastranpy/bdf/cards/card_interfaces_additional.py
nastranpy/bdf/cards/card_list.py
nastranpy/bdf/cards/card_set.py
nastranpy/bdf/cards/class_factory.py
nastranpy/bdf/cards/coord_card.py
nastranpy/bdf/cards/coord_system.py
nastranpy/bdf/cards/elem_card.py
nastranpy/bdf/cards/filters.py
nastranpy/bdf/cards/grid_card.py
nastranpy/bdf/cards/include_card.py
nastranpy/bdf/cards/padding.py
nastranpy/bdf/cards/set_card.py
nastranpy/bdf/cards/subscheme.py
nastranpy/bdf/cards/vector_card.py
nastranpy-0.1.2.dist-info/DESCRIPTION.rst
nastranpy-0.1.2.dist-info/METADATA
nastranpy-0.1.2.dist-info/RECORD
nastranpy-0.1.2.dist-info/WHEEL
nastranpy-0.1.2.dist-info/metadata.json
nastranpy-0.1.2.dist-info/top_level.txt
