Metadata-Version: 2.0
Name: nastranpy
Version: 0.1.2
Summary: A library to interact with nastran models
Home-page: https://github.com/alvarosanz/nastranpy
Author: Álvaro Sanz Oriz
Author-email: alvaro.sanz.oriz@gmail.com
License: MIT
Keywords: NASTRAN FEM engineering
Platform: UNKNOWN
Requires-Python: >=3.3
Requires-Dist: numpy
